verification/verilog/fixed_to_fp.v
module fixed_to_fp (
    input clk,
    input sign_i,
    input integer_i,
    input [18:0] fractional_i,
    output [31:0] fp_o
);
    /* Given that we know the exponent will always be negative, we can exploit this to get an extremely
    fast and compact method of converting from fixed point to IEEE-754 floating point. */

    reg cursor; // this tracks whether the MSB has been encountered yet
    reg [18:0] cursor_array;
    reg [7:0] exponent;
    reg [31:0] fp_reg;

    assign fp_o = fp_reg;

    always @(posedge clk) begin

        // check special cases first
        if (integer_i == 1) begin
            if (sign_i == 1) fp_reg <= 32'b1;
            else fp_reg <= 32'b0;
        end else begin

            /* SPECIAL ALGORITHM */
            /* We keep a cursor to keep track of whether the MSB has been encountered yet or not.
            The value of the cursor is then compared with each input bit using cur = !cur AND in.
            This will evaluate to:
                0 for all leading zeros
                1 for the first 1 encountered in the input
                0 for all subsequent 1s or 0s
            Storing the value of the cursor in an output each time will allow us to then select an
            exponent using a simple multiplexer.
            */

            // reset values
            cursor = 0;
            cursor_array = 0;

            // perform sweep for MSB. These must be blocking statements.
            cursor_array[18] = ~cursor & fractional_i[18];
            cursor_array[17] = ~cursor & fractional_i[17];
            cursor_array[16] = ~cursor & fractional_i[16];
            cursor_array[15] = ~cursor & fractional_i[15];
            cursor_array[14] = ~cursor & fractional_i[14];
            cursor_array[13] = ~cursor & fractional_i[13];
            cursor_array[12] = ~cursor & fractional_i[12];
            cursor_array[11] = ~cursor & fractional_i[11];
            cursor_array[10] = ~cursor & fractional_i[10];
            cursor_array[9] = ~cursor & fractional_i[9];
            cursor_array[8] = ~cursor & fractional_i[8];
            cursor_array[7] = ~cursor & fractional_i[7];
            cursor_array[6] = ~cursor & fractional_i[6];
            cursor_array[5] = ~cursor & fractional_i[5];
            cursor_array[4] = ~cursor & fractional_i[4];
            cursor_array[3] = ~cursor & fractional_i[3];
            cursor_array[2] = ~cursor & fractional_i[2];
            cursor_array[1] = ~cursor & fractional_i[1];
            cursor_array[0] = ~cursor & fractional_i[0];

            // now we just select the exponent, this translates to a simple mux.
            // Not the actual exponent, then add 128 to take care of both the IEE-754 bias and two's complement
            // in one go.
            $display("\nCursor array is: %b", cursor_array);

            case(cursor_array)
                19'b1000000000000000000: exponent = ~(8'b00000001) + 8'b10000000;
                19'b0100000000000000000: exponent = ~(8'b00000010) + 8'b10000000;
                19'b0010000000000000000: exponent = ~(8'b00000011) + 8'b10000000;
                19'b0001000000000000000: exponent = ~(8'b00000100) + 8'b10000000;
                19'b0000100000000000000: exponent = ~(8'b00000101) + 8'b10000000;
                19'b0000010000000000000: exponent = ~(8'b00000110) + 8'b10000000;
                19'b0000001000000000000: exponent = ~(8'b00000111) + 8'b10000000;
                19'b0000000100000000000: exponent = ~(8'b00001000) + 8'b10000000;
                19'b0000000010000000000: exponent = ~(8'b00001001) + 8'b10000000;
                19'b0000000001000000000: exponent = ~(8'b00001010) + 8'b10000000;
                19'b0000000000100000000: exponent = ~(8'b00001011) + 8'b10000000;
                19'b0000000000010000000: exponent = ~(8'b00001100) + 8'b10000000;
                19'b0000000000001000000: exponent = ~(8'b00001101) + 8'b10000000;
                19'b0000000000000100000: exponent = ~(8'b00001110) + 8'b10000000;
                19'b0000000000000010000: exponent = ~(8'b00001111) + 8'b10000000;
                19'b0000000000000001000: exponent = ~(8'b00010000) + 8'b10000000;
                19'b0000000000000000100: exponent = ~(8'b00010001) + 8'b10000000;
                19'b0000000000000000010: exponent = ~(8'b00010010) + 8'b10000000;
                19'b0000000000000000001: exponent = ~(8'b00010011) + 8'b10000000;
                default: exponent = 8'b0;
            endcase
            $display("Exponent is %b\n", exponent);

            fp_reg <= {sign_i, exponent, fractional_i << exponent, 4'b0};
        end
    end
endmodule

verification/verilog/fp_to_fixed.v
module fp_to_fixed (
    input clk,
    input [31:0] fp_i, // floating point input
    output sign_o, // sign of fixed-point
    output reg integer_o, // integer part of fixed-point
    output reg [18:0] fractional_o // fractional part of fixed-point
);

    reg [7:0] exponent;
    reg [7:0] unbiased_exponent;
    reg [22:0] significand;

    assign sign_o = fp_i[31]; // keep the same sign
    assign exponent = fp_i[30:23]; // extract exponent
    assign significand = fp_i[22:0]; // extract significand
    assign unbiased_exponent = ~(exponent - 127 - 8'b00000001); // unbias component using two's complement

    always @(posedge clk) begin

        reg integer_part = 1'b1; // for denormalising the significand
        reg [22:0] fractional_part = significand;

        if (unbiased_exponent[0] == 1) begin
            fractional_part = {integer_part, fractional_part[22:1]}; // sign extend
            integer_part = 1'b0;
        end

        if (unbiased_exponent[1] == 1) begin
            fractional_part = {1'b0, integer_part, fractional_part[22:2]}; // sign extend
            integer_part = 1'b0;
        end

        if (unbiased_exponent[2] == 1) begin
            fractional_part = {3'b0, integer_part, fractional_part[22:4]}; // sign extend
            integer_part = 1'b0;
        end

        if (unbiased_exponent[3] == 1) begin
            fractional_part = {7'b0, integer_part, fractional_part[22:8]}; // sign extend
            integer_part = 1'b0;
        end

        if (unbiased_exponent[4] == 1) begin
            fractional_part = {15'b0, integer_part, fractional_part[22:16]}; // sign extend
            integer_part = 1'b0;
        end

        integer_o <= integer_part;
        fractional_o <= fractional_part[22:4]; // KEEP ONLY BITS REQUIRED BY MONTE-CARLO RESULTS
        $display("full fractional part: %b\n", fractional_part);
        $display("truncated fractional part: %b\n", fractional_o);

    end
endmodule;

verification/verilog/top.v
module top (
    input clk,
    input [31:0] in,
    output sign_out,
    output int_out, // only one bit needed due to specs
    output [18:0] frac_out,
    output [31:0] fp_out
);

fp_to_fixed fp_converter (
    .clk(clk),
    .fp_i(in),
    .sign_o(sign_out),
    .fractional_o(frac_out),
    .integer_o(int_out)
);

fixed_to_fp fixed_converter (
    .clk(clk),
    .sign_i(sign_out),
    .integer_i(int_out),
    .fractional_i(frac_out),
    .fp_o(fp_out)
);

endmodule;

verification/top.vcd
$version Generated by VerilatedVcd $end
$date Sun Mar 10 23:05:55 2024 $end
$timescale 1ps $end

 $scope module TOP $end
  $var wire  1 ) clk $end
  $var wire 32 . fp_out [31:0] $end
  $var wire 19 - frac_out [18:0] $end
  $var wire 32 * in [31:0] $end
  $var wire  1 , int_out $end
  $var wire  1 + sign_out $end
  $scope module top $end
   $var wire  1 ) clk $end
   $var wire 32 . fp_out [31:0] $end
   $var wire 19 - frac_out [18:0] $end
   $var wire 32 * in [31:0] $end
   $var wire  1 , int_out $end
   $var wire  1 + sign_out $end
   $scope module fixed_converter $end
    $var wire  1 ) clk $end
    $var wire  1 # cursor $end
    $var wire 19 $ cursor_array [18:0] $end
    $var wire  8 % exponent [7:0] $end
    $var wire 32 . fp_o [31:0] $end
    $var wire 32 & fp_reg [31:0] $end
    $var wire 19 - fractional_i [18:0] $end
    $var wire  1 , integer_i $end
    $var wire  1 + sign_i $end
   $upscope $end
   $scope module fp_converter $end
    $var wire  1 ) clk $end
    $var wire  8 / exponent [7:0] $end
    $var wire 32 * fp_i [31:0] $end
    $var wire 19 - fractional_o [18:0] $end
    $var wire  1 , integer_o $end
    $var wire  1 + sign_o $end
    $var wire 23 1 significand [22:0] $end
    $var wire  8 0 unbiased_exponent [7:0] $end
    $scope module unnamedblk1 $end
     $var wire 23 ( fractional_part [22:0] $end
     $var wire  1 ' integer_part $end
    $upscope $end
   $upscope $end
  $upscope $end
 $upscope $end
$enddefinitions $end


#0
0#
b0000000000000000000 $
b00000000 %
b00000000000000000000000000000000 &
0'
b00000000000000000000000 (
0)
b00111110000000000000000000000000 *
0+
0,
b0000000000000000000 -
b00000000000000000000000000000000 .
b01111100 /
b00000011 0
b00000000000000000000000 1
#1
1)
#2
0)
b00111101100000000000000000000000 *
b01111011 /
b00000100 0
#3
b00010000000000000000000 (
1)
b0001000000000000000 -
#4
0)
b10111101100000000000000000000000 *
#5
b0001000000000000000 $
b01111011 %
b00111101100000000000000000000000 &
1)
1+
b00111101100000000000000000000000 .
#6
0)
b00000000000000000000000000000000 *
b00000000 /
b01111111 0
#7
b10111101100000000000000000000000 &
b00000000000000000000000 (
1)
0+
b0000000000000000000 -
b10111101100000000000000000000000 .
#8
0)
b00111111100000000000000000000000 *
b01111111 /
b00000000 0
#9
b0000000000000000000 $
b00000000 %
b00000000000000000000000000000000 &
1'
1)
1,
b00000000000000000000000000000000 .
#10
0)
b10111111100000000000000000000000 *
#11
1)
1+
